github_tools/__init__.py
github_tools/gh_create_milestone.py
github_tools/gh_issue_templates.py
github_tools/gh_repos.py
github_tools/github_issue_templates.py
github_tools/github_tools_examples.py
github_tools_beta-0.0.27.dist-info/METADATA
github_tools_beta-0.0.27.dist-info/WHEEL
github_tools_beta-0.0.27.dist-info/top_level.txt
github_tools_beta-0.0.27.dist-info/RECORD
