Metadata-Version: 2.1
Name: github-tools-beta
Version: 0.0.27
Summary: Template and testing purposes
Requires-Dist: requests
